plorts/__init__.py
plorts/_version.py
plorts/legend.py
plorts/palettes.py
plorts/plorts-col.mplstyle
plorts/plorts-cool.mplstyle
plorts/plorts-halfcol.mplstyle
plorts/plorts-neon.mplstyle
plorts/plorts-onehalfcol.mplstyle
plorts/plorts-print.mplstyle
plorts/plorts-twocol.mplstyle
plorts/plorts-warm.mplstyle
plorts/plorts-web.mplstyle
plorts/plorts.mplstyle
plorts/plotting.py
plorts/style.py
plorts-0.7.9.dist-info/licenses/LICENSE
plorts-0.7.9.dist-info/METADATA
plorts-0.7.9.dist-info/WHEEL
plorts-0.7.9.dist-info/top_level.txt
plorts-0.7.9.dist-info/RECORD
